{ "data": [
{
  "payload": "mdnsaje 153",
  "sec": 1658691540,
  "rssi": -100,
  "snr": -5.5,
  "freq": 433000000,
  "sf": 7,
  "bw": 125000,
  "cr": 8
},{
  "payload": "mensaje 155",
  "sec": 1658691542,
  "rssi": -102,
  "snr": -6.75,
  "freq": 433000000,
  "sf": 7,
  "bw": 125000,
  "cr": 8
},{
  "payload": "mensaje 127",
  "sec": 1658691545,
  "rssi": -101,
  "snr": -6.75,
  "freq": 433000000,
  "sf": 7,
  "bw": 125000,
  "cr": 8
},{
  "payload": "mensaje 158",
  "sec": 1658691546,
  "rssi": -99,
  "snr": -6,
  "freq": 433000000,
  "sf": 7,
  "bw": 125000,
  "cr": 8
},{
  "payload": "mensaäe 161",
  "sec": 1658691549,
  "rssi": -99,
  "snr": -5,
  "freq": 433000000,
  "sf": 7,
  "bw": 125000,
  "cr": 8
},{
  "payload": "mensaje 162",
  "sec": 1658691550,
  "rssi": -100,
  "snr": -5,
  "freq": 433000000,
  "sf": 7,
  "bw": 125000,
  "cr": 8
},{
  "payload": "mensaje 163",
  "sec": 1658691552,
  "rssi": -101,
  "snr": -6.5,
  "freq": 433000000,
  "sf": 7,
  "bw": 125000,
  "cr": 8
},{
  "payload": "mensaje 164",
  "sec": 1658691553,
  "rssi": -100,
  "snr": -5.5,
  "freq": 433000000,
  "sf": 7,
  "bw": 125000,
  "cr": 8
},{
  "payload": "mensaje 1f6",
  "sec": 1658691555,
  "rssi": -100,
  "snr": -6,
  "freq": 433000000,
  "sf": 7,
  "bw": 125000,
  "cr": 8
},{
  "payload": "ge˛zaje 172",
  "sec": 1658691562,
  "rssi": -98,
  "snr": -8,
  "freq": 433000000,
  "sf": 7,
  "bw": 125000,
  "cr": 8
},{
  "payload": "oencaje 173",
  "sec": 1658691563,
  "rssi": -99,
  "snr": -6.5,
  "freq": 433000000,
  "sf": 7,
  "bw": 125000,
  "cr": 8
},{
  "payload": "mÖn3ajE1=",
  "sec": 1658691568,
  "rssi": -103,
  "snr": -7.5,
  "freq": 433000000,
  "sf": 7,
  "bw": 125000,
  "cr": 8
},{
  "payload": "mensaje 17à",
  "sec": 1658691569,
  "rssi": -100,
  "snr": -6.5,
  "freq": 433000000,
  "sf": 7,
  "bw": 125000,
  "cr": 8
},{
  "payload": "mensae 179",
  "sec": 1658691570,
  "rssi": -101,
  "snr": -7,
  "freq": 433000000,
  "sf": 7,
  "bw": 125000,
  "cr": 8
},{
  "payload": "^vgiq{l 180",
  "sec": 1658691571,
  "rssi": -101,
  "snr": -5.25,
  "freq": 433000000,
  "sf": 7,
  "bw": 125000,
  "cr": 8
},{
  "payload": "menscde <íc",
  "sec": 1658691573,
  "rssi": -103,
  "snr": -7,
  "freq": 433000000,
  "sf": 7,
  "bw": 125000,
  "cr": 8
},{
  "payload": "}ensaje 183",
  "sec": 1658691575,
  "rssi": -101,
  "snr": -5.25,
  "freq": 433000000,
  "sf": 7,
  "bw": 125000,
  "cr": 8
},{
  "payload": "Õen*≠j• —8ó",
  "sec": 1658691577,
  "rssi": -102,
  "snr": -8.25,
  "freq": 433000000,
  "sf": 7,
  "bw": 125000,
  "cr": 8
},{
  "payload": "he>vaje 187",
  "sec": 1658691578,
  "rssi": -101,
  "snr": -6.75,
  "freq": 433000000,
  "sf": 7,
  "bw": 125000,
  "cr": 8
},{
  "payload": "mens1je 187",
  "sec": 1658691579,
  "rssi": -101,
  "snr": -6.5,
  "freq": 433000000,
  "sf": 7,
  "bw": 125000,
  "cr": 8
},{
  "payload": "ldnsaje 188",
  "sec": 1658691580,
  "rssi": -101,
  "snr": -5.75,
  "freq": 433000000,
  "sf": 7,
  "bw": 125000,
  "cr": 8
},{
  "payload": "meLqq{e,19?",
  "sec": 1658691586,
  "rssi": -101,
  "snr": -7.25,
  "freq": 433000000,
  "sf": 7,
  "bw": 125000,
  "cr": 8
},{
  "payload": "men√qje 198",
  "sec": 1658691592,
  "rssi": -100,
  "snr": -7.5,
  "freq": 433000000,
  "sf": 7,
  "bw": 125000,
  "cr": 8
},{
  "payload": "Õ≈nsºÍË\u0000202",
  "sec": 1658691594,
  "rssi": -101,
  "snr": -7.5,
  "freq": 433000000,
  "sf": 7,
  "bw": 125000,
  "cr": 8
},{
  "payload": "˝‰ˆ\"aje¿—72",
  "sec": 1658693000,
  "rssi": -101,
  "snr": -8.25,
  "freq": 433000000,
  "sf": 7,
  "bw": 125000,
  "cr": 8
},{
  "payload": "hÖéw`l˝:g_",
  "sec": 1658693001,
  "rssi": -100,
  "snr": -7.25,
  "freq": 433000000,
  "sf": 7,
  "bw": 125000,
  "cr": 8
},{
  "payload": "oeLsaje 179",
  "sec": 1658693008,
  "rssi": -99,
  "snr": -7,
  "freq": 433000000,
  "sf": 7,
  "bw": 125000,
  "cr": 8
},{
  "payload": "`ﬁ’(a\ne11(2",
  "sec": 1658693013,
  "rssi": -100,
  "snr": -8.5,
  "freq": 433000000,
  "sf": 7,
  "bw": 125000,
  "cr": 8
},{
  "payload": "meNsjÂ =85",
  "sec": 1658693015,
  "rssi": -100,
  "snr": -7.5,
  "freq": 433000000,
  "sf": 7,
  "bw": 125000,
  "cr": 8
},{
  "payload": "çenìoj;¿167",
  "sec": 1658694437,
  "rssi": -102,
  "snr": -8,
  "freq": 433000000,
  "sf": 7,
  "bw": 125000,
  "cr": 8
},{
  "payload": "mensaje 191",
  "sec": 1658694465,
  "rssi": -102,
  "snr": -6.25,
  "freq": 433000000,
  "sf": 7,
  "bw": 125000,
  "cr": 8
},{
  "payload": "›e≥~π⁄e-149",
  "sec": 1658694475,
  "rssi": -101,
  "snr": -8.75,
  "freq": 433000000,
  "sf": 7,
  "bw": 125000,
  "cr": 8
},]}
